setup.py
UniSR/__init__.py
pyUniSR.egg-info/PKG-INFO
pyUniSR.egg-info/SOURCES.txt
pyUniSR.egg-info/dependency_links.txt
pyUniSR.egg-info/top_level.txt