Metadata-Version: 1.1
Name: pyUniSR
Version: 0.0.7
Summary: Python class to access studenti.unisr.it (Univerity Vita-Salute San Raffaele, Milano)
Home-page: https://github.com/nico202/pyUniSR
Author: Nicolo Balzarotti
Author-email: anothersms@gmail.com
License: GPLv2
Keywords: unisr class milano university raffaele
Platform: UNKNOWN
Classifier: Development Status :: 3 - Alpha
Classifier: Topic :: Utilities
Classifier: License :: OSI Approved :: GNU General Public License v2 (GPLv2)
